libraebookmanager/__init__.py
libraebookmanager/html_generator.py
libraebookmanager/main.py
libraebookmanager/scanner.py
libraebookmanager-0.5.dist-info/METADATA
libraebookmanager-0.5.dist-info/WHEEL
libraebookmanager-0.5.dist-info/entry_points.txt
libraebookmanager-0.5.dist-info/top_level.txt
libraebookmanager-0.5.dist-info/RECORD
