Metadata-Version: 2.1
Name: libraebookmanager
Version: 0.5
Summary: libra is a Python package designed to help you organize and explore your eBook collection.
Home-page: https://github.com/arazshah/libra
Author: Araz Shah
Author-email: araz.shah@gmail.com
Requires-Python: >=3.6
Requires-Dist: pillow
Requires-Dist: python-magic
Requires-Dist: PyPDF2
Requires-Dist: ebooklib
Requires-Dist: pymupdf
